django_celery_boost/__init__.py
django_celery_boost/admin.py
django_celery_boost/models.py
django_celery_boost/signals.py
django_celery_boost/version.py
django_celery_boost/templates/admin/celery_boost/change_form.html
django_celery_boost/templates/admin/celery_boost/inspect.html
django_celery_boost/templates/admin/celery_boost/queue.html
django_celery_boost/templates/admin/celery_boost/terminate.html
django_celery_boost-0.6.2.dist-info/METADATA
django_celery_boost-0.6.2.dist-info/WHEEL
django_celery_boost-0.6.2.dist-info/licenses/LICENSE
django_celery_boost-0.6.2.dist-info/RECORD
