Metadata-Version: 2.4
Name: django-celery-boost
Version: 0.6.2
Summary: Django Abstract Model to work with Celery
Project-URL: downloads, https://github.com/unicef/django-celery-boost
Project-URL: homepage, https://github.com/unicef/django-celery-boost
Author-email: sax <s.apostolico@gmail.com>
Maintainer-email: sax <s.apostolico@gmail.com>
License-File: LICENSE
Classifier: Programming Language :: Python :: 3 :: Only
Classifier: Programming Language :: Python :: 3.9
Classifier: Programming Language :: Python :: 3.10
Classifier: Programming Language :: Python :: 3.11
Classifier: Programming Language :: Python :: 3.12
Classifier: Programming Language :: Python :: 3.13
Requires-Python: >=3.9
Requires-Dist: celery>=5.4
Requires-Dist: django-admin-extra-buttons
Requires-Dist: django-concurrency
Requires-Dist: sentry-sdk
